aiostandalone/__init__.py
aiostandalone/aiosignal.py
aiostandalone/app.py
aiostandalone/log.py
aio_standalone-0.2.0.dist-info/LICENSE
aio_standalone-0.2.0.dist-info/METADATA
aio_standalone-0.2.0.dist-info/WHEEL
aio_standalone-0.2.0.dist-info/top_level.txt
aio_standalone-0.2.0.dist-info/RECORD
